sparkplug_core/__init__.py
sparkplug_core/enums/__init__.py
sparkplug_core/enums/subscription_type.py
sparkplug_core/middleware/__init__.py
sparkplug_core/middleware/camelcase.py
sparkplug_core/middleware/timezone.py
sparkplug_core/models/__init__.py
sparkplug_core/models/base_model.py
sparkplug_core/models/subscriber_mixin.py
sparkplug_core/pagination/__init__.py
sparkplug_core/pagination/default_pagination.py
sparkplug_core/redis/__init__.py
sparkplug_core/redis/content_subscription.py
sparkplug_core/rules/__init__.py
sparkplug_core/rules/has_admin_access.py
sparkplug_core/rules/has_primary_access.py
sparkplug_core/rules/is_anonymous.py
sparkplug_core/rules/is_authenticated.py
sparkplug_core/serializers/__init__.py
sparkplug_core/serializers/search_term.py
sparkplug_core/tests/__init__.py
sparkplug_core/tests/rules/__init__.py
sparkplug_core/tests/rules/test_has_admin_access.py
sparkplug_core/tests/rules/test_has_primary_access.py
sparkplug_core/tests/rules/test_is_anonymous.py
sparkplug_core/tests/rules/test_is_authenticated.py
sparkplug_core/tests/utils/__init__.py
sparkplug_core/tests/utils/test_asdict_exclude_none.py
sparkplug_core/tests/utils/test_enforce_auth.py
sparkplug_core/tests/utils/test_enforce_permission.py
sparkplug_core/tests/utils/test_get_pagination_start_end.py
sparkplug_core/tests/utils/test_get_validated_dataclass.py
sparkplug_core/types.py
sparkplug_core/utils/__init__.py
sparkplug_core/utils/asdict_exclude_none.py
sparkplug_core/utils/build_cache_key.py
sparkplug_core/utils/enforce_auth.py
sparkplug_core/utils/enforce_permission.py
sparkplug_core/utils/get_paginated_response.py
sparkplug_core/utils/get_pagination_start_end.py
sparkplug_core/utils/get_timezones.py
sparkplug_core/utils/get_validated_dataclass.py
sparkplug_core/utils/send_admin_action.py
sparkplug_core/utils/send_client_action.py
sparkplug_core/utils/send_mail.py
sparkplug_core/utils/send_mail_from_template.py
sparkplug_core/utils/socket_send.py
sparkplug_api_core-1.1.5.dist-info/METADATA
sparkplug_api_core-1.1.5.dist-info/WHEEL
sparkplug_api_core-1.1.5.dist-info/RECORD
