Metadata-Version: 2.3
Name: sparkplug-api-core
Version: 1.1.5
Summary: Core package for building a Sparkplug app
License: MIT
Author: Sparkplug Marcus
Author-email: sparkplugmarcus@gmail.com
Requires-Python: >=3.11,<4.0
Classifier: License :: OSI Approved :: MIT License
Classifier: Programming Language :: Python :: 3
Classifier: Programming Language :: Python :: 3.11
Classifier: Programming Language :: Python :: 3.12
Classifier: Programming Language :: Python :: 3.13
Requires-Dist: Django (>=5.2.4,<5.3.0)
Requires-Dist: boto3 (>=1.39.4,<1.40.0)
Requires-Dist: channels (==4.2.2)
Requires-Dist: channels-redis (>=4.2.1,<4.3.0)
Requires-Dist: daphne (>=4.2.1,<4.3.0)
Requires-Dist: django-anymail (>=13.0,<13.1)
Requires-Dist: django-cors-headers (>=4.7.0,<4.8.0)
Requires-Dist: django-extensions (>=4.1,<4.2)
Requires-Dist: django-redis (>=6.0.0,<6.1.0)
Requires-Dist: django-rest-knox (>=5.0.2,<5.1.0)
Requires-Dist: django-split-settings (>=1.3.2,<1.4.0)
Requires-Dist: django-storages (>=1.14.6,<1.15.0)
Requires-Dist: djangorestframework (>=3.16.0,<3.17.0)
Requires-Dist: djangorestframework-camel-case (>=1.4.2,<1.5.0)
Requires-Dist: djangorestframework-dataclasses (>=1.4.0,<1.5.0)
Requires-Dist: huey (>=2.5.3,<2.6.0)
Requires-Dist: psycopg2-binary (>=2.9.10,<2.10.0)
Requires-Dist: pytest (>=8.4.1,<8.5.0)
Requires-Dist: python-dateutil (>=2.9.0,<2.10.0)
Requires-Dist: python-decouple (>=3.8,<3.9)
Requires-Dist: python-json-logger (>=3.3.0,<3.4.0)
Requires-Dist: rules (>=3.5,<3.6)
Requires-Dist: shortuuid (>=1.0.13,<1.1.0)
Requires-Dist: walrus (>=0.9.5,<0.10.0)
